{
    "elements": [
		{ "id": "grail", "induces": []},
		{ "id": "heart", "induces": []},
		{ "id": "lantern", "induces": []},
		{ "id": "moth", "induces": []},
    
        {
            "id": "refresh",
            "label": "Обновление",
            "isAspect": true,
            "isHidden": true,
        },
        {
            "id": "copy",
            "label": "Копирование",
            "isAspect": true,
            "isHidden": true,
        },
        {
            "id": "merge.activate",
            "label": "Активация соединения",
            "isAspect": true,
            "isHidden": true,
        },
        {
            "id": "merge.deactivate",
            "label": "Активация соединения",
            "isAspect": true,
            "isHidden": true,
        },
        {
            "id": "action.weaken",
            "label": "Действие: ослабить",
            "isAspect": true,
            "isHidden": true,
        },
        {
            "id": "action.neutralize",
            "label": "Действие: нейтрализовать",
            "isAspect": true,
            "isHidden": true,
        },
        {
            "id": "action.disease.heal",
            "label": "Действие: полечить болезнь",
            "isAspect": true,
            "isHidden": true,
        },
        
        {
            "id": "potion.merge.inactive",
            "label": "Неактивное зелье соединения",
            "isAspect": true,
            "isHidden": true,
        },
        {
            "id": "remove.at.the.end",
            "label": "После окончания реакции удалить этот объект.",
            "isAspect": true,
            "isHidden": true,
        },
        
        
        {
            "id": "stasis.extend",
            "label": "Расширение стазиса",
            "isAspect": true,
            "isHidden": true,
        },
        {
            "id": "stasis.interrupt",
            "label": "Прерывание стазиса",
            "isAspect": true,
            "isHidden": true,
        },
        
        
        {
            "id": "modifiable",
            "label": "Модифицируемое",
            "isAspect": true,
            "isHidden": true,
        },
        
        {
            "id": "potion.strengthen.or.absolute",
            "label": "Зелье силы или абсолюта",
            "isAspect": true,
            "isHidden": true,
        },
        {
            "id": "_alchemist.reputation",
            "label": "Репутация",
            "description": "Мирская молва — морская волна.",
            "isAspect": true,
        }, 
    ]
}